polars_luxical-0.1.2.dist-info/METADATA
polars_luxical-0.1.2.dist-info/WHEEL
polars_luxical.libs/libgcc_s-6d2d9dc8.so.1
polars_luxical/__init__.py
polars_luxical/_polars_luxical.cpython-313t-x86_64-linux-musl.so
polars_luxical/utils.py
polars_luxical-0.1.2.dist-info/RECORD
