Metadata-Version: 2.4
Name: polars_luxical
Version: 0.1.2
Classifier: Development Status :: 4 - Beta
Classifier: Intended Audience :: Developers
Classifier: License :: OSI Approved :: Apache Software License
Classifier: Operating System :: MacOS
Classifier: Operating System :: POSIX :: Linux
Classifier: Programming Language :: Rust
Classifier: Programming Language :: Python :: 3
Classifier: Programming Language :: Python :: 3.11
Classifier: Programming Language :: Python :: 3.12
Classifier: Programming Language :: Python :: 3.13
Requires-Dist: polars>=1.36.0
Requires-Dist: polars-distance>=0.5.3
Summary: A Polars plugin for fast lexical text embeddings
Author-email: Louis Maddox <louismmx@gmail.com>
License: Apache-2.0
Requires-Python: >=3.11, <3.14
